{
    "mapping": {
        "0": "Crime Against Property",
        "1": "Crime Against Public",
        "2": "Sex Offenses",
        "3": "Offence Against Person",
        "4": "Non-Criminal|Other Offense|Warrants|Missing Person|Suspicious OCC",
        "5": "Runaway"
    },
    "LARCENY/THEFT": {"category": 0},
    "VANDALISM": {"category": 1},
    "NON-CRIMINAL": {"category": 4},
    "ARSON": {"category": 0},
    "FRAUD": {"category": 0},
    "OTHER OFFENSES": {"category": 4},
    "FORGERY/COUNTERFEITING": {"category": 0},
    "ASSAULT": {"category": 3},
    "WARRANTS": {"category": 4},
    "WEAPON LAWS": {"category": 1},
    "MISSING PERSON": {"category": 4},
    "DRUG/NARCOTIC": {"category": 1},
    "STOLEN PROPERTY": {"category": 0},
    "VEHICLE THEFT": {"category": 0},
    "BURGLARY": {"category": 0},
    "SUSPICIOUS OCC": {"category": 4},
    "RECOVERED VEHICLE": {"category": 0},
    "ROBBERY": {"category": 0},
    "TRESPASS": {"category": 3},
    "SECONDARY CODES": {"category": 0},
    "SUICIDE": {"category": 1},
    "DRUNKENNESS": {"category": 1},
    "BRIBERY": {"category": 0},
    "SEX OFFENSES, FORCIBLE": {"category": 2},
    "KIDNAPPING": {"category": 3},
    "EMBEZZLEMENT": {"category": 0},
    "PROSTITUTION": {"category": 2},
    "RUNAWAY": {"category": 5},
    "LIQUOR LAWS": {"category": 1},
    "DRIVING UNDER THE INFLUENCE": {"category": 1},
    "DISORDERLY CONDUCT": {"category": 1},
    "EXTORTION": {"category": 0},
    "FAMILY OFFENSES": {"category": 3},
    "LOITERING": {"category": 1},
    "SEX OFFENSES, NON FORCIBLE": {"category": 2},
    "BAD CHECKS": {"category": 0},
    "GAMBLING": {"category": 0},
    "PORNOGRAPHY/OBSCENE MAT": {"category": 2}
}
